fortes_webservice_wrapper/__init__.py
fortes_webservice_wrapper/_version.py
fortes_webservice_wrapper/constants.py
fortes_webservice_wrapper/models/__init__.py
fortes_webservice_wrapper/models/base.py
fortes_webservice_wrapper/wrapper/__init__.py
fortes_webservice_wrapper/wrapper/fortes_ws.py
fortes_webservice_wrapper/wrapper/soap.py
fortes_webservice_wrapper-0.0.1.dist-info/LICENSE
fortes_webservice_wrapper-0.0.1.dist-info/METADATA
fortes_webservice_wrapper-0.0.1.dist-info/WHEEL
fortes_webservice_wrapper-0.0.1.dist-info/top_level.txt
fortes_webservice_wrapper-0.0.1.dist-info/RECORD
